{
    "serviceName": "virtual-desk",
    "serviceDescription": "Painel de controle da plataforma VirtualDesk",
    "repositoryNamespace": "VirtualDeskRepo",
    "packageName": "virtual-desk",
    "packageType": "webapp",
    "packagePath": "Platform.Module/Applications.layer/virtual-desk.webapp",
    "startupParams": {
        "port"                              : "7001",
        "serverName"                        : "KadiskVirtualDeskWebAppInstance",
        "serverManagerUrl"                  : "http://virtualdesk.app.local:9000/server-manager/status",
        "RT_ENV_GENERATED_DIR_NAME"         : ".generated_data",
        "isWatch"                           : true,
        "installDataDirPath"                : "~/EcosystemData",
        "ecosystemDefaultsFileRelativePath" : "./config-files/ecosystem-defaults.json",
        "secretKey"                         : "kajsdhfg&(#Ndg",
        "repositoryStorageServerManagerUrl" : "/server-manager/status",
        "iamStorageServerManagerUrl"        : "/server-manager/status"
    },
    "socketParams":{
        "repositoryStorageSocketPath": "repository-storage-manager.app.sock",
        "iamStorageSocketPath": "iam.app.sock"
    },
    "storageParams":{
        "eventManagerServiceStorageFilePath" : "event-manager-service.sqlite",
        "instanceMonitoringManagerServiceStorageFilePath": "instance-monitoring-manager-service.sqlite",
        "myWorkbenchRepositoriesUploadDirPath": "my-workbench-uploded-repositories"
    },
    "ports": [],
    "networkmode": "host"
}